<?xml version="1.0" encoding="UTF-8"?>
<resources>
    <string name="Login">メールアドレス</string>
    <string name="M_Test_Key_01">こんにちは、このサンプルファイルはMemsourceデモ用のみです。</string>
    <string name="M_Test_Key_02">すごい。素敵な仕事。これは本当に役立ちます!何か新しいものが必要ですか?私はそれらのすべてを持っています!私はそれらを必要としません。</string>
    <string name="M_Test_Key_03">ゲームは、モバイルで利用可能なサバイバルシューティングゲームです。</string>
    <string name="M_Test_Key_game_content_0">追加キーとメッセージ</string>
    <string name="M_Test_Key_game_content_01">新シーズンは03/08/2020 18:00 GMT+ 8から始まります</string>
    <string name="M_Test_Key_game_content_02">ああ、それは..●「FFC500」テスト用![-]</string>
    <string name="M_Test_Key_game_content_03">追加キーとメッセージ</string>
    <string name="M_Test_Key_game_content_04">メッセージをもっと見る</string>
    <string name="M_Test_Key_game_content_05">キーが1つ追加されます</string>
    <string name="M_Test_Key_game_content_06">これは最新キー。</string>
    <string name="M_Test_Key_game_content_07">キーが1つ追加されます</string>
    <string name="Memsource logo">メムソース</string>
    <string name="Message">あなたのお宅をより美しく！</string>
    <string name="Message2">テスト2</string>
    <string name="pwd">パスワード</string>
    <string name="Start">スタート</string>
</resources>
